{
    "sheltering": {
        "next": 1674724776,
        "local": "01/26/2023 02:19:36"
    },
    "at_groups": {
        "next": 1674714727,
        "local": "01/25/2023 23:32:07"
    },
    "sell_quick_box": {
        "next": 1674716386,
        "local": "01/25/2023 23:59:46"
    },
    "check_box": {
        "next": 1674715519,
        "local": "01/25/2023 23:45:19"
    },
    "fiery_mine": {
        "next": 1674715939,
        "local": "01/25/2023 23:52:19"
    },
    "get_taven": {
        "next": 1674716948,
        "local": "01/26/2023 00:09:08"
    },
    "trade": {
        "next": 1674717057,
        "local": "01/26/2023 00:10:57"
    },
    "daily_train": {
        "log_unfinished": {
            "inf": [
                1,
                500
            ],
            "cav": [
                1,
                500
            ],
            "spe": [
                1,
                500
            ],
            "bow": [
                1,
                500
            ]
        },
        "log_reset_date": {
            "reset": "2023-01-26"
        },
        "next": 1674716907,
        "local": "01/26/2023 00:08:27"
    },
    "bank_claim": {
        "next": 1674702436,
        "local": "01/25/2023 20:07:16"
    },
    "explore_drag": {
        "next": 1674716222,
        "local": "01/25/2023 23:57:02"
    },
    "daily_gift": {
        "next": 1674778199,
        "local": "01/26/2023 17:09:59"
    },
    "auto_transport_rss": {
        "next": 1674697206,
        "local": "01/25/2023 18:40:06"
    },
    "balanced_farms": {
        "next": 1674702270,
        "local": "01/25/2023 20:04:30"
    },
    "bliz_elite_trial": {
        "next": 1674769537,
        "local": "01/26/2023 14:45:37"
    },
    "expeditions": {
        "next": 1674717426,
        "local": "01/26/2023 00:17:06"
    },
    "camp_hof": {
        "next": 1674723131,
        "local": "01/26/2023 01:52:11"
    },
    "get_discount": {
        "next": 1674717161,
        "local": "01/26/2023 00:12:41"
    },
    "enter_code": {
        "next": 1674717260,
        "local": "01/26/2023 00:14:20"
    },
    "complete_all_trials": {
        "next": 1674717142,
        "local": "01/26/2023 00:12:22"
    },
    "daily_msg": {
        "next": 1674704436,
        "local": "01/25/2023 20:40:36"
    },
    "raffle_drag": {
        "next": 1674691799,
        "local": "01/25/2023 17:09:59"
    },
    "heal_all": {
        "next": 1674684615,
        "local": "01/25/2023 15:10:15"
    },
    "read_mails": {
        "next": 1674925244,
        "local": "01/28/2023 10:00:44"
    }
}