{
    "sheltering": {
        "next": 1670700276,
        "local": "12/10/2022 12:24:36"
    },
    "at_groups": {
        "next": 1670693458,
        "local": "12/10/2022 10:30:58"
    },
    "sell_quick_box": {
        "next": 1670692017,
        "local": "12/10/2022 10:06:57"
    },
    "check_box": {
        "next": 1670692099,
        "local": "12/10/2022 10:08:19"
    },
    "fiery_mine": {
        "next": 1670692298,
        "local": "12/10/2022 10:11:38"
    },
    "get_taven": {
        "next": 1670692342,
        "local": "12/10/2022 10:12:22"
    },
    "trade": {
        "next": 1670692423,
        "local": "12/10/2022 10:13:43"
    },
    "daily_train": {
        "log_unfinished": {
            "inf": [
                1,
                500
            ],
            "cav": [
                1,
                500
            ],
            "spe": [
                1,
                500
            ],
            "bow": [
                1,
                500
            ]
        },
        "log_reset_date": {
            "reset": "2022-12-10"
        },
        "next": 1670692616,
        "local": "12/10/2022 10:16:56"
    },
    "bank_claim": {
        "next": 1670692712,
        "local": "12/10/2022 10:18:32"
    },
    "balanced_farms": {
        "next": 1670691926,
        "local": "12/10/2022 10:05:26"
    },
    "get_vip_box": {
        "next": 1670692741,
        "local": "12/10/2022 10:19:01"
    },
    "auto_transport_rss": {
        "next": 1670693389,
        "local": "12/10/2022 10:29:49"
    }
}