{
    "sheltering": {
        "next": 1672968195,
        "local": "01/05/2023 18:23:15"
    },
    "at_groups": {
        "next": 1672960259,
        "local": "01/05/2023 16:10:59"
    },
    "sell_quick_box": {
        "next": 1672942924,
        "local": "01/05/2023 11:22:04"
    },
    "check_box": {
        "next": 1672941629,
        "local": "01/05/2023 11:00:29"
    },
    "fiery_mine": {
        "next": 1672942440,
        "local": "01/05/2023 11:14:00"
    },
    "get_taven": {
        "next": 1672958457,
        "local": "01/05/2023 15:40:57"
    },
    "trade": {
        "next": 1672958416,
        "local": "01/05/2023 15:40:16"
    },
    "daily_train": {
        "log_reset_date": {
            "reset": "2023-01-05"
        },
        "log_unfinished": {
            "spe": [
                1,
                500
            ],
            "bow": [
                1,
                500
            ]
        },
        "next": 1672962656,
        "local": "01/05/2023 16:50:56"
    },
    "bank_claim": {
        "next": 1672892213,
        "local": "01/04/2023 21:16:53"
    },
    "balanced_farms": {
        "next": 1672892741,
        "local": "01/04/2023 21:25:41"
    },
    "auto_transport_rss": {
        "next": 1672874078,
        "local": "01/04/2023 16:14:38"
    },
    "expeditions": {
        "next": 1672872730,
        "local": "01/04/2023 15:52:10"
    },
    "camp_hof": {
        "next": 1672949616,
        "local": "01/05/2023 13:13:36"
    },
    "get_discount": {
        "next": 1672872454,
        "local": "01/04/2023 15:47:34"
    },
    "training_ground": {
        "next": 1672873608,
        "local": "01/04/2023 16:06:48"
    },
    "explore_drag": {
        "next": 1672892100,
        "local": "01/04/2023 21:15:00"
    },
    "daily_gift": {
        "next": 1672877399,
        "local": "01/04/2023 17:09:59"
    },
    "bliz_elite_trial": {
        "next": 1672873951,
        "local": "01/04/2023 16:12:31"
    },
    "enter_code": {
        "next": 1672892358,
        "local": "01/04/2023 21:19:18"
    },
    "complete_all_trials": {
        "next": 1672877403,
        "local": "01/04/2023 17:10:03"
    },
    "daily_msg": {
        "next": 1672873820,
        "local": "01/04/2023 16:10:20"
    },
    "raffle_drag": {
        "next": 1672877399,
        "local": "01/04/2023 17:09:59"
    }
}