{
    "sheltering": {
        "next": 1671287128,
        "local": "12/17/2022 07:25:28"
    },
    "at_groups": {
        "next": 1671276643,
        "local": "12/17/2022 04:30:43"
    },
    "sell_quick_box": {
        "next": 1671277970,
        "local": "12/17/2022 04:52:50"
    },
    "check_box": {
        "next": 1671276720,
        "local": "12/17/2022 04:32:00"
    },
    "fiery_mine": {
        "next": 1671277707,
        "local": "12/17/2022 04:48:27"
    },
    "get_taven": {
        "next": 1671277767,
        "local": "12/17/2022 04:49:27"
    },
    "trade": {
        "next": 1671277938,
        "local": "12/17/2022 04:52:18"
    },
    "daily_train": {
        "log_reset_date": {
            "reset": "2022-12-17"
        },
        "log_unfinished": {
            "inf": [
                1,
                500
            ],
            "cav": [
                1,
                500
            ],
            "spe": [
                1,
                500
            ],
            "bow": [
                1,
                500
            ]
        },
        "next": 1671277856,
        "local": "12/17/2022 04:50:56"
    },
    "bank_claim": {
        "next": 1671278853,
        "local": "12/17/2022 05:07:33"
    },
    "balanced_farms": {
        "next": 1671278524,
        "local": "12/17/2022 05:02:04"
    },
    "get_vip_box": {
        "next": 1671261887,
        "local": "12/17/2022 00:24:47"
    },
    "auto_transport_rss": {
        "next": 1671279878,
        "local": "12/17/2022 05:24:38"
    },
    "expeditions": {
        "next": 1671278766,
        "local": "12/17/2022 05:06:06"
    },
    "camp_hof": {
        "next": 1671284882,
        "local": "12/17/2022 06:48:02"
    },
    "get_discount": {
        "next": 1671278595,
        "local": "12/17/2022 05:03:15"
    },
    "training_ground": {
        "next": 1671262001,
        "local": "12/17/2022 00:26:41"
    }
}