{
    "sheltering": {
        "next": 1670972964,
        "local": "12/13/2022 16:09:24"
    },
    "at_groups": {
        "next": 1670967013,
        "local": "12/13/2022 14:30:13"
    },
    "sell_quick_box": {
        "next": 1670964752,
        "local": "12/13/2022 13:52:32"
    },
    "check_box": {
        "next": 1670965582,
        "local": "12/13/2022 14:06:22"
    },
    "fiery_mine": {
        "next": 1670964664,
        "local": "12/13/2022 13:51:04"
    },
    "get_taven": {
        "next": 1670964840,
        "local": "12/13/2022 13:54:00"
    },
    "trade": {
        "next": 1670964928,
        "local": "12/13/2022 13:55:28"
    },
    "daily_train": {
        "log_reset_date": {
            "reset": "2022-12-13"
        },
        "log_unfinished": {
            "inf": [
                1,
                500
            ],
            "cav": [
                1,
                500
            ],
            "spe": [
                1,
                500
            ],
            "bow": [
                1,
                500
            ]
        },
        "next": 1670964806,
        "local": "12/13/2022 13:53:26"
    },
    "bank_claim": {
        "next": 1670965004,
        "local": "12/13/2022 13:56:44"
    },
    "balanced_farms": {
        "next": 1670965114,
        "local": "12/13/2022 13:58:34"
    },
    "get_vip_box": {
        "next": 1670964247,
        "local": "12/13/2022 13:44:07"
    },
    "auto_transport_rss": {
        "next": 1670965498,
        "local": "12/13/2022 14:04:58"
    },
    "expeditions": {
        "next": 1670965277,
        "local": "12/13/2022 14:01:17"
    },
    "camp_hof": {
        "next": 1670964567,
        "local": "12/13/2022 13:49:27"
    },
    "training_ground": {
        "next": 1670964399,
        "local": "12/13/2022 13:46:39"
    }
}