{
    "sheltering": {
        "next": 1673551825,
        "local": "01/12/2023 12:30:25"
    },
    "at_groups": {
        "next": 1673544698,
        "local": "01/12/2023 10:31:38"
    },
    "sell_quick_box": {
        "next": 1673542887,
        "local": "01/12/2023 10:01:27"
    },
    "check_box": {
        "next": 1673542381,
        "local": "01/12/2023 09:53:01"
    },
    "fiery_mine": {
        "next": 1673542953,
        "local": "01/12/2023 10:02:33"
    },
    "get_taven": {
        "next": 1673543410,
        "local": "01/12/2023 10:10:10"
    },
    "trade": {
        "next": 1673543517,
        "local": "01/12/2023 10:11:57"
    },
    "daily_train": {
        "log_unfinished": {
            "spe": [
                1,
                500
            ],
            "bow": [
                1,
                500
            ]
        },
        "log_reset_date": {
            "reset": "2023-01-12"
        },
        "next": 1673547522,
        "local": "01/12/2023 11:18:42"
    },
    "bank_claim": {
        "next": 1673544209,
        "local": "01/12/2023 10:23:29"
    },
    "explore_drag": {
        "next": 1673533547,
        "local": "01/12/2023 07:25:47"
    },
    "daily_gift": {
        "next": 1673568599,
        "local": "01/12/2023 17:09:59"
    },
    "auto_transport_rss": {
        "next": 1673544242,
        "local": "01/12/2023 10:24:02"
    },
    "balanced_farms": {
        "next": 1673543473,
        "local": "01/12/2023 10:11:13"
    },
    "bliz_elite_trial": {
        "next": 1673596508,
        "local": "01/13/2023 00:55:08"
    },
    "expeditions": {
        "next": 1673524512,
        "local": "01/12/2023 04:55:12"
    },
    "training_ground": {
        "next": 1673524263,
        "local": "01/12/2023 04:51:03"
    },
    "camp_hof": {
        "next": 1673543299,
        "local": "01/12/2023 10:08:19"
    },
    "get_discount": {
        "next": 1673524281,
        "local": "01/12/2023 04:51:21"
    },
    "enter_code": {
        "next": 1673524536,
        "local": "01/12/2023 04:55:36"
    },
    "complete_all_trials": {
        "next": 1673525213,
        "local": "01/12/2023 05:06:53"
    },
    "daily_msg": {
        "next": 1673524681,
        "local": "01/12/2023 04:58:01"
    },
    "raffle_drag": {
        "next": 1673524839,
        "local": "01/12/2023 05:00:39"
    },
    "heal_all": {
        "next": 1673525607,
        "local": "01/12/2023 05:13:27"
    },
    "read_mails": {
        "next": 1673852044,
        "local": "01/15/2023 23:54:04"
    }
}