{
    "sheltering": {
        "next": 1674123618,
        "local": "01/19/2023 03:20:18"
    },
    "at_groups": {
        "next": 1674115444,
        "local": "01/19/2023 01:04:04"
    },
    "sell_quick_box": {
        "next": 1674114933,
        "local": "01/19/2023 00:55:33"
    },
    "check_box": {
        "next": 1674114362,
        "local": "01/19/2023 00:46:02"
    },
    "fiery_mine": {
        "next": 1674115525,
        "local": "01/19/2023 01:05:25"
    },
    "get_taven": {
        "next": 1674115715,
        "local": "01/19/2023 01:08:35"
    },
    "trade": {
        "next": 1674115680,
        "local": "01/19/2023 01:08:00"
    },
    "daily_train": {
        "log_unfinished": {
            "spe": [
                1,
                500
            ],
            "bow": [
                1,
                500
            ]
        },
        "log_reset_date": {
            "reset": "2023-01-19"
        },
        "next": 1674119827,
        "local": "01/19/2023 02:17:07"
    },
    "bank_claim": {
        "next": 1674513485,
        "local": "01/23/2023 15:38:05"
    },
    "explore_drag": {
        "next": 1674110904,
        "local": "01/18/2023 23:48:24"
    },
    "daily_gift": {
        "next": 1674101994,
        "local": "01/18/2023 21:19:54"
    },
    "auto_transport_rss": {
        "next": 1674115341,
        "local": "01/19/2023 01:02:21"
    },
    "balanced_farms": {
        "next": 1674101812,
        "local": "01/18/2023 21:16:52"
    },
    "bliz_elite_trial": {
        "next": 1674101942,
        "local": "01/18/2023 21:19:02"
    },
    "expeditions": {
        "next": 1674101172,
        "local": "01/18/2023 21:06:12"
    },
    "camp_hof": {
        "next": 1674121512,
        "local": "01/19/2023 02:45:12"
    },
    "get_discount": {
        "next": 1674101190,
        "local": "01/18/2023 21:06:30"
    },
    "enter_code": {
        "next": 1674101214,
        "local": "01/18/2023 21:06:54"
    },
    "complete_all_trials": {
        "next": 1674101292,
        "local": "01/18/2023 21:08:12"
    },
    "daily_msg": {
        "next": 1674101472,
        "local": "01/18/2023 21:11:12"
    },
    "raffle_drag": {
        "next": 1674101450,
        "local": "01/18/2023 21:10:50"
    },
    "heal_all": {
        "next": 1674101898,
        "local": "01/18/2023 21:18:18"
    },
    "read_mails": {
        "next": 1674392034,
        "local": "01/22/2023 05:53:54"
    }
}