{
    "sheltering": {
        "next": 1675001878,
        "local": "01/29/2023 07:17:58"
    },
    "at_groups": {
        "next": 1674992409,
        "local": "01/29/2023 04:40:09"
    },
    "sell_quick_box": {
        "next": 1674993860,
        "local": "01/29/2023 05:04:20"
    },
    "check_box": {
        "next": 1674992483,
        "local": "01/29/2023 04:41:23"
    },
    "fiery_mine": {
        "next": 1674993368,
        "local": "01/29/2023 04:56:08"
    },
    "get_taven": {
        "next": 1674994381,
        "local": "01/29/2023 05:13:01"
    },
    "trade": {
        "next": 1674994074,
        "local": "01/29/2023 05:07:54"
    },
    "daily_train": {
        "log_reset_date": {
            "reset": "2023-01-29"
        },
        "log_unfinished": {
            "spe": [
                1,
                500
            ],
            "bow": [
                1,
                500
            ]
        },
        "next": 1674998538,
        "local": "01/29/2023 06:22:18"
    },
    "bank_claim": {
        "next": 1674974725,
        "local": "01/28/2023 23:45:25"
    },
    "balanced_farms": {
        "next": 1674975740,
        "local": "01/29/2023 00:02:20"
    },
    "auto_transport_rss": {
        "next": 1675007770,
        "local": "01/29/2023 08:56:10"
    },
    "bliz_elite_trial": {
        "next": 1675060239,
        "local": "01/29/2023 23:30:39"
    },
    "camp_hof": {
        "next": 1674993886,
        "local": "01/29/2023 05:04:46"
    },
    "expeditions": {
        "next": 1674976554,
        "local": "01/29/2023 00:15:54"
    },
    "get_discount": {
        "next": 1674789505,
        "local": "01/26/2023 20:18:25"
    },
    "enter_code": {
        "next": 1674857464,
        "local": "01/27/2023 15:11:04"
    },
    "daily_msg": {
        "next": 1674878046,
        "local": "01/27/2023 20:54:06"
    },
    "explore_drag": {
        "next": 1674886188,
        "local": "01/27/2023 23:09:48"
    },
    "daily_gift": {
        "next": 1675037399,
        "local": "01/29/2023 17:09:59"
    },
    "raffle_drag": {
        "next": 1674864599,
        "local": "01/27/2023 17:09:59"
    },
    "heal_all": {
        "next": 1674530273,
        "local": "01/23/2023 20:17:53"
    },
    "read_mails": {
        "next": 1674529507,
        "local": "01/23/2023 20:05:07"
    }
}