{
    "sheltering": {
        "next": 1674897534,
        "local": "01/28/2023 02:18:54"
    },
    "at_groups": {
        "next": 1674887956,
        "local": "01/27/2023 23:39:16"
    },
    "sell_quick_box": {
        "next": 1674889230,
        "local": "01/28/2023 00:00:30"
    },
    "check_box": {
        "next": 1674890899,
        "local": "01/28/2023 00:28:19"
    },
    "fiery_mine": {
        "next": 1674888966,
        "local": "01/27/2023 23:56:06"
    },
    "get_taven": {
        "next": 1674875375,
        "local": "01/27/2023 20:09:35"
    },
    "trade": {
        "next": 1674875488,
        "local": "01/27/2023 20:11:28"
    },
    "daily_train": {
        "log_reset_date": {
            "reset": "2023-01-28"
        },
        "log_unfinished": {
            "cav": [
                1,
                500
            ],
            "spe": [
                1,
                500
            ],
            "bow": [
                1,
                500
            ]
        },
        "next": 1674879705,
        "local": "01/27/2023 21:21:45"
    },
    "bank_claim": {
        "next": 1674875633,
        "local": "01/27/2023 20:13:53"
    },
    "balanced_farms": {
        "next": 1674889826,
        "local": "01/28/2023 00:10:26"
    },
    "auto_transport_rss": {
        "next": 1674889169,
        "local": "01/27/2023 23:59:29"
    },
    "explore_drag": {
        "next": 1674899022,
        "local": "01/28/2023 02:43:42"
    },
    "daily_gift": {
        "next": 1674864599,
        "local": "01/27/2023 17:09:59"
    },
    "bliz_elite_trial": {
        "next": 1674888943,
        "local": "01/27/2023 23:55:43"
    },
    "expeditions": {
        "next": 1674875836,
        "local": "01/27/2023 20:17:16"
    },
    "camp_hof": {
        "next": 1674881587,
        "local": "01/27/2023 21:53:07"
    },
    "get_discount": {
        "next": 1674889846,
        "local": "01/28/2023 00:10:46"
    },
    "enter_code": {
        "next": 1674875859,
        "local": "01/27/2023 20:17:39"
    },
    "complete_all_trials": {
        "next": 1674889902,
        "local": "01/28/2023 00:11:42"
    },
    "daily_msg": {
        "next": 1674928625,
        "local": "01/28/2023 10:57:05"
    },
    "raffle_drag": {
        "next": 1674950999,
        "local": "01/28/2023 17:09:59"
    },
    "heal_all": {
        "next": 1674735148,
        "local": "01/26/2023 05:12:28"
    },
    "read_mails": {
        "next": 1675028948,
        "local": "01/29/2023 14:49:08"
    }
}