{
    "sheltering": {
        "next": 1670563587,
        "local": "12/08/2022 22:26:27"
    },
    "at_groups": {
        "next": 1670557645,
        "local": "12/08/2022 20:47:25"
    },
    "sell_quick_box": {
        "next": 1670556120,
        "local": "12/08/2022 20:22:00"
    },
    "check_box": {
        "next": 1670555845,
        "local": "12/08/2022 20:17:25"
    },
    "fiery_mine": {
        "next": 1670555282,
        "local": "12/08/2022 20:08:02"
    },
    "get_taven": {
        "next": 1670555317,
        "local": "12/08/2022 20:08:37"
    },
    "trade": {
        "next": 1670555405,
        "local": "12/08/2022 20:10:05"
    },
    "daily_train": {
        "log_unfinished": {
            "inf": [
                1,
                500
            ],
            "cav": [
                1,
                500
            ],
            "spe": [
                1,
                500
            ],
            "bow": [
                1,
                500
            ]
        },
        "log_reset_date": {
            "reset": "2022-12-09"
        },
        "next": 1670555459,
        "local": "12/08/2022 20:10:59"
    },
    "bank_claim": {
        "next": 1670555534,
        "local": "12/08/2022 20:12:14"
    },
    "balanced_farms": {
        "next": 1670555645,
        "local": "12/08/2022 20:14:05"
    },
    "get_vip_box": {
        "next": 1670555761,
        "local": "12/08/2022 20:16:01"
    },
    "auto_transport_rss": {
        "next": 1670556340,
        "local": "12/08/2022 20:25:40"
    },
    "expeditions": {
        "next": 1670556018,
        "local": "12/08/2022 20:20:18"
    },
    "camp_hof": {
        "next": 1670555187,
        "local": "12/08/2022 20:06:27"
    },
    "training_ground": {
        "next": 1670555732,
        "local": "12/08/2022 20:15:32"
    }
}