{
    "sheltering": {
        "next": 1674278355,
        "local": "01/20/2023 22:19:15"
    },
    "at_groups": {
        "next": 1674269411,
        "local": "01/20/2023 19:50:11"
    },
    "sell_quick_box": {
        "next": 1674270405,
        "local": "01/20/2023 20:06:45"
    },
    "check_box": {
        "next": 1674270125,
        "local": "01/20/2023 20:02:05"
    },
    "fiery_mine": {
        "next": 1674270817,
        "local": "01/20/2023 20:13:37"
    },
    "get_taven": {
        "next": 1674270935,
        "local": "01/20/2023 20:15:35"
    },
    "trade": {
        "next": 1674251248,
        "local": "01/20/2023 14:47:28"
    },
    "daily_train": {
        "log_unfinished": {
            "spe": [
                1,
                500
            ],
            "bow": [
                1,
                500
            ]
        },
        "log_reset_date": {
            "reset": "2023-01-20"
        },
        "next": 1674255428,
        "local": "01/20/2023 15:57:08"
    },
    "bank_claim": {
        "next": 1674251948,
        "local": "01/20/2023 14:59:08"
    },
    "balanced_farms": {
        "next": 1674252505,
        "local": "01/20/2023 15:08:25"
    },
    "auto_transport_rss": {
        "next": 1674162092,
        "local": "01/19/2023 14:01:32"
    },
    "bliz_elite_trial": {
        "next": 1674252049,
        "local": "01/20/2023 15:00:49"
    },
    "camp_hof": {
        "next": 1674270756,
        "local": "01/20/2023 20:12:36"
    },
    "expeditions": {
        "next": 1674253085,
        "local": "01/20/2023 15:18:05"
    },
    "get_discount": {
        "next": 1674252610,
        "local": "01/20/2023 15:10:10"
    },
    "enter_code": {
        "next": 1674252589,
        "local": "01/20/2023 15:09:49"
    },
    "complete_all_trials": {
        "next": 1674252667,
        "local": "01/20/2023 15:11:07"
    },
    "daily_msg": {
        "next": 1674291391,
        "local": "01/21/2023 01:56:31"
    },
    "explore_drag": {
        "next": 1674262071,
        "local": "01/20/2023 17:47:51"
    },
    "daily_gift": {
        "next": 1674259799,
        "local": "01/20/2023 17:09:59"
    },
    "raffle_drag": {
        "next": 1674259799,
        "local": "01/20/2023 17:09:59"
    }
}