{
    "sheltering": {
        "next": 1671700696,
        "local": "12/22/2022 02:18:16"
    },
    "at_groups": {
        "next": 1671693033,
        "local": "12/22/2022 00:10:33"
    },
    "sell_quick_box": {
        "next": 1671691938,
        "local": "12/21/2022 23:52:18"
    },
    "check_box": {
        "next": 1671691960,
        "local": "12/21/2022 23:52:40"
    },
    "fiery_mine": {
        "next": 1671691898,
        "local": "12/21/2022 23:51:38"
    },
    "get_taven": {
        "next": 1671691999,
        "local": "12/21/2022 23:53:19"
    },
    "trade": {
        "next": 1671692073,
        "local": "12/21/2022 23:54:33"
    },
    "daily_train": {
        "log_reset_date": {
            "reset": "2022-12-22"
        },
        "log_unfinished": {
            "inf": [
                1,
                500
            ],
            "cav": [
                1,
                500
            ],
            "spe": [
                1,
                500
            ],
            "bow": [
                1,
                500
            ]
        },
        "next": 1671691978,
        "local": "12/21/2022 23:52:58"
    },
    "bank_claim": {
        "next": 1671692106,
        "local": "12/21/2022 23:55:06"
    },
    "balanced_farms": {
        "next": 1671692740,
        "local": "12/22/2022 00:05:40"
    },
    "auto_transport_rss": {
        "next": 1671692761,
        "local": "12/22/2022 00:06:01"
    },
    "bliz_elite_trial": {
        "next": 1671678218,
        "local": "12/21/2022 20:03:38"
    },
    "camp_hof": {
        "next": 1671684182,
        "local": "12/21/2022 21:43:02"
    },
    "expeditions": {
        "next": 1671677839,
        "local": "12/21/2022 19:57:19"
    },
    "get_discount": {
        "next": 1671677675,
        "local": "12/21/2022 19:54:35"
    },
    "training_ground": {
        "next": 1671677663,
        "local": "12/21/2022 19:54:23"
    },
    "enter_code": {
        "next": 1671677525,
        "local": "12/21/2022 19:52:05"
    },
    "complete_all_trials": {
        "next": 1671677592,
        "local": "12/21/2022 19:53:12"
    },
    "daily_msg": {
        "next": 1671677854,
        "local": "12/21/2022 19:57:34"
    },
    "explore_drag": {
        "next": 1671702178,
        "local": "12/22/2022 02:42:58"
    },
    "daily_gift": {
        "next": 1671678187,
        "local": "12/21/2022 20:03:07"
    },
    "raffle_drag": {
        "next": 1671678326,
        "local": "12/21/2022 20:05:26"
    },
    "heal_all": {
        "next": 1671678063,
        "local": "12/21/2022 20:01:03"
    },
    "read_mails": {
        "next": 1672073372,
        "local": "12/26/2022 09:49:32"
    }
}