{
    "sheltering": {
        "next": 1672791477,
        "local": "01/03/2023 17:17:57"
    },
    "at_groups": {
        "next": 1672781497,
        "local": "01/03/2023 14:31:37"
    },
    "sell_quick_box": {
        "next": 1672783620,
        "local": "01/03/2023 15:07:00"
    },
    "check_box": {
        "next": 1672781691,
        "local": "01/03/2023 14:34:51"
    },
    "fiery_mine": {
        "next": 1672782748,
        "local": "01/03/2023 14:52:28"
    },
    "get_taven": {
        "next": 1672783351,
        "local": "01/03/2023 15:02:31"
    },
    "trade": {
        "next": 1672783570,
        "local": "01/03/2023 15:06:10"
    },
    "daily_train": {
        "log_unfinished": {},
        "log_reset_date": {
            "reset": "2023-01-03"
        },
        "next": 1672790447,
        "local": "01/03/2023 17:00:47"
    },
    "bank_claim": {
        "next": 1672766126,
        "local": "01/03/2023 10:15:26"
    },
    "explore_drag": {
        "next": 1672793362,
        "local": "01/03/2023 17:49:22"
    },
    "balanced_farms": {
        "next": 1672766014,
        "local": "01/03/2023 10:13:34"
    },
    "daily_gift": {
        "next": 1672790999,
        "local": "01/03/2023 17:09:59"
    },
    "auto_transport_rss": {
        "next": 1672766164,
        "local": "01/03/2023 10:16:04"
    },
    "bliz_elite_trial": {
        "next": 1672791057,
        "local": "01/03/2023 17:10:57"
    },
    "camp_hof": {
        "next": 1672783116,
        "local": "01/03/2023 14:58:36"
    },
    "get_discount": {
        "next": 1672747704,
        "local": "01/03/2023 05:08:24"
    },
    "expeditions": {
        "next": 1672784099,
        "local": "01/03/2023 15:14:59"
    },
    "training_ground": {
        "next": 1672783793,
        "local": "01/03/2023 15:09:53"
    },
    "enter_code": {
        "next": 1672747728,
        "local": "01/03/2023 05:08:48"
    },
    "complete_all_trials": {
        "next": 1672783870,
        "local": "01/03/2023 15:11:10"
    },
    "daily_msg": {
        "next": 1672768771,
        "local": "01/03/2023 10:59:31"
    },
    "raffle_drag": {
        "next": 1672790999,
        "local": "01/03/2023 17:09:59"
    }
}