{
    "sheltering": {
        "next": 1673137078,
        "local": "01/07/2023 17:17:58"
    },
    "at_groups": {
        "next": 1673126815,
        "local": "01/07/2023 14:26:55"
    },
    "sell_quick_box": {
        "next": 1673128167,
        "local": "01/07/2023 14:49:27"
    },
    "check_box": {
        "next": 1673129229,
        "local": "01/07/2023 15:07:09"
    },
    "fiery_mine": {
        "next": 1673127909,
        "local": "01/07/2023 14:45:09"
    },
    "get_taven": {
        "next": 1673128536,
        "local": "01/07/2023 14:55:36"
    },
    "trade": {
        "next": 1673128498,
        "local": "01/07/2023 14:54:58"
    },
    "daily_train": {
        "log_unfinished": {
            "inf": [
                1,
                500
            ],
            "cav": [
                1,
                500
            ],
            "spe": [
                1,
                500
            ],
            "bow": [
                1,
                500
            ]
        },
        "log_reset_date": {
            "reset": "2023-01-07"
        },
        "next": 1673128383,
        "local": "01/07/2023 14:53:03"
    },
    "bank_claim": {
        "next": 1673129348,
        "local": "01/07/2023 15:09:08"
    },
    "explore_drag": {
        "next": 1673139329,
        "local": "01/07/2023 17:55:29"
    },
    "daily_gift": {
        "next": 1673136599,
        "local": "01/07/2023 17:09:59"
    },
    "balanced_farms": {
        "next": 1673128342,
        "local": "01/07/2023 14:52:22"
    },
    "auto_transport_rss": {
        "next": 1673128978,
        "local": "01/07/2023 15:02:58"
    },
    "bliz_elite_trial": {
        "next": 1673129032,
        "local": "01/07/2023 15:03:52"
    },
    "camp_hof": {
        "next": 1673128277,
        "local": "01/07/2023 14:51:17"
    },
    "expeditions": {
        "next": 1673129721,
        "local": "01/07/2023 15:15:21"
    },
    "get_discount": {
        "next": 1673093450,
        "local": "01/07/2023 05:10:50"
    },
    "training_ground": {
        "next": 1673093685,
        "local": "01/07/2023 05:14:45"
    },
    "enter_code": {
        "next": 1673093474,
        "local": "01/07/2023 05:11:14"
    },
    "complete_all_trials": {
        "next": 1673093556,
        "local": "01/07/2023 05:12:36"
    },
    "daily_msg": {
        "next": 1673099353,
        "local": "01/07/2023 06:49:13"
    },
    "raffle_drag": {
        "next": 1673136599,
        "local": "01/07/2023 17:09:59"
    },
    "heal_all": {
        "next": 1673060761,
        "local": "01/06/2023 20:06:01"
    },
    "read_mails": {
        "next": 1672954993,
        "local": "01/05/2023 14:43:13"
    }
}