{
    "sheltering": {
        "next": 1674313565,
        "local": "01/21/2023 08:06:05"
    },
    "at_groups": {
        "next": 1674303868,
        "local": "01/21/2023 05:24:28"
    },
    "sell_quick_box": {
        "next": 1674305439,
        "local": "01/21/2023 05:50:39"
    },
    "check_box": {
        "next": 1674304058,
        "local": "01/21/2023 05:27:38"
    },
    "fiery_mine": {
        "next": 1674305176,
        "local": "01/21/2023 05:46:16"
    },
    "get_taven": {
        "next": 1674305886,
        "local": "01/21/2023 05:58:06"
    },
    "trade": {
        "next": 1674305851,
        "local": "01/21/2023 05:57:31"
    },
    "daily_train": {
        "log_reset_date": {
            "reset": "2023-01-21"
        },
        "log_unfinished": {
            "spe": [
                1,
                500
            ],
            "bow": [
                1,
                500
            ]
        },
        "next": 1674309940,
        "local": "01/21/2023 07:05:40"
    },
    "bank_claim": {
        "next": 1674305746,
        "local": "01/21/2023 05:55:46"
    },
    "balanced_farms": {
        "next": 1674308880,
        "local": "01/21/2023 06:48:00"
    },
    "auto_transport_rss": {
        "next": 1674319524,
        "local": "01/21/2023 09:45:24"
    },
    "explore_drag": {
        "next": 1674305973,
        "local": "01/21/2023 05:59:33"
    },
    "daily_gift": {
        "next": 1674346199,
        "local": "01/21/2023 17:09:59"
    },
    "bliz_elite_trial": {
        "next": 1674305693,
        "local": "01/21/2023 05:54:53"
    },
    "camp_hof": {
        "next": 1674304967,
        "local": "01/21/2023 05:42:47"
    },
    "expeditions": {
        "next": 1674305398,
        "local": "01/21/2023 05:49:58"
    },
    "get_discount": {
        "next": 1674305991,
        "local": "01/21/2023 05:59:51"
    },
    "enter_code": {
        "next": 1674305499,
        "local": "01/21/2023 05:51:39"
    }
}