{
    "sheltering": {
        "next": 1675074322,
        "local": "01/30/2023 03:25:22"
    },
    "at_groups": {
        "next": 1675065996,
        "local": "01/30/2023 01:06:36"
    },
    "sell_quick_box": {
        "next": 1675065376,
        "local": "01/30/2023 00:56:16"
    },
    "check_box": {
        "next": 1675065211,
        "local": "01/30/2023 00:53:31"
    },
    "fiery_mine": {
        "next": 1675065549,
        "local": "01/30/2023 00:59:09"
    },
    "get_taven": {
        "next": 1675065932,
        "local": "01/30/2023 01:05:32"
    },
    "trade": {
        "next": 1675066049,
        "local": "01/30/2023 01:07:29"
    },
    "daily_train": {
        "log_reset_date": {
            "reset": "2023-01-30"
        },
        "log_unfinished": {
            "spe": [
                1,
                500
            ],
            "bow": [
                1,
                500
            ]
        },
        "next": 1675070376,
        "local": "01/30/2023 02:19:36"
    },
    "bank_claim": {
        "next": 1675601234,
        "local": "02/05/2023 05:47:14"
    },
    "balanced_farms": {
        "next": 1675051663,
        "local": "01/29/2023 21:07:43"
    },
    "explore_drag": {
        "next": 1675065681,
        "local": "01/30/2023 01:01:21"
    },
    "daily_gift": {
        "next": 1675051837,
        "local": "01/29/2023 21:10:37"
    },
    "auto_transport_rss": {
        "next": 1675079818,
        "local": "01/30/2023 04:56:58"
    },
    "bliz_elite_trial": {
        "next": 1675051708,
        "local": "01/29/2023 21:08:28"
    },
    "camp_hof": {
        "next": 1675065780,
        "local": "01/30/2023 01:03:00"
    },
    "expeditions": {
        "next": 1675051576,
        "local": "01/29/2023 21:06:16"
    }
}