{
    "sheltering": {
        "next": 1673137167,
        "local": "01/07/2023 17:19:27"
    },
    "at_groups": {
        "next": 1673130060,
        "local": "01/07/2023 15:21:00"
    },
    "sell_quick_box": {
        "next": 1673127891,
        "local": "01/07/2023 14:44:51"
    },
    "check_box": {
        "next": 1673126684,
        "local": "01/07/2023 14:24:44"
    },
    "fiery_mine": {
        "next": 1673127637,
        "local": "01/07/2023 14:40:37"
    },
    "get_taven": {
        "next": 1673128351,
        "local": "01/07/2023 14:52:31"
    },
    "trade": {
        "next": 1673128650,
        "local": "01/07/2023 14:57:30"
    },
    "daily_train": {
        "log_reset_date": {
            "reset": "2023-01-07"
        },
        "log_unfinished": {
            "inf": [
                1,
                500
            ],
            "cav": [
                1,
                500
            ],
            "spe": [
                1,
                500
            ],
            "bow": [
                1,
                500
            ]
        },
        "next": 1673128446,
        "local": "01/07/2023 14:54:06"
    },
    "bank_claim": {
        "next": 1673128882,
        "local": "01/07/2023 15:01:22"
    },
    "balanced_farms": {
        "next": 1673129713,
        "local": "01/07/2023 15:15:13"
    },
    "auto_transport_rss": {
        "next": 1673128690,
        "local": "01/07/2023 14:58:10"
    },
    "camp_hof": {
        "next": 1673134589,
        "local": "01/07/2023 16:36:29"
    },
    "explore_drag": {
        "next": 1673102874,
        "local": "01/07/2023 07:47:54"
    },
    "daily_gift": {
        "next": 1673136599,
        "local": "01/07/2023 17:09:59"
    },
    "bliz_elite_trial": {
        "next": 1673129622,
        "local": "01/07/2023 15:13:42"
    },
    "expeditions": {
        "next": 1673129577,
        "local": "01/07/2023 15:12:57"
    },
    "get_discount": {
        "next": 1673129045,
        "local": "01/07/2023 15:04:05"
    },
    "training_ground": {
        "next": 1673129026,
        "local": "01/07/2023 15:03:46"
    },
    "enter_code": {
        "next": 1673129071,
        "local": "01/07/2023 15:04:31"
    },
    "complete_all_trials": {
        "next": 1673129151,
        "local": "01/07/2023 15:05:51"
    },
    "daily_msg": {
        "next": 1673129175,
        "local": "01/07/2023 15:06:15"
    },
    "raffle_drag": {
        "next": 1673129338,
        "local": "01/07/2023 15:08:58"
    }
}