{
    "check_box": {
        "next": 1670814947,
        "local": "12/11/2022 20:15:47"
    },
    "bank_claim": {
        "next": 1670815534,
        "local": "12/11/2022 20:25:34"
    },
    "bliz_elite_trial": {
        "next": 1670901182,
        "local": "12/12/2022 20:13:02"
    },
    "get_discount": {
        "next": 1670815545,
        "local": "12/11/2022 20:25:45"
    },
    "get_bonus": {
        "next": 1670815552,
        "local": "12/11/2022 20:25:52"
    },
    "enter_code": {
        "next": 1670815721,
        "local": "12/11/2022 20:28:41"
    },
    "complete_all_trials": {
        "next": 1670815815,
        "local": "12/11/2022 20:30:15"
    }
}